amazon/__init__.py
amazon/apps.py
amazon/urls.py
amazon/utils.py
amazon/account/__init__.py
amazon/account/actions.py
amazon/account/admin.py
amazon/account/apps.py
amazon/account/models.py
amazon/account/urls.py
amazon/account/views.py
amazon/account/migrations/0001_initial.py
amazon/account/migrations/0002_amazonuseraccount_marketplace_user_account.py
amazon/account/migrations/__init__.py
amazon/account/serializers/__init__.py
amazon/account/serializers/amazon_user_account/__init__.py
amazon/account/serializers/amazon_user_account/base.py
amazon/account/serializers/amazon_user_account/create.py
amazon/account/tests/__init__.py
amazon/account/tests/factories.py
amazon/account/tests/test_views.py
amazon/api/__init__.py
amazon/api/amazon_access.py
amazon/api/amazon_action.py
amazon/api/core/__init__.py
amazon/api/core/feeds.py
amazon/api/core/finances.py
amazon/api/core/inbound_shipments.py
amazon/api/core/inventory.py
amazon/api/core/mws.py
amazon/api/core/offamazonpayments.py
amazon/api/core/orders.py
amazon/api/core/products.py
amazon/api/core/recommendations.py
amazon/api/core/reports.py
amazon/api/core/sellers.py
amazon/api/core/utils.py
amazon/category/__init__.py
amazon/category/admin.py
amazon/category/apps.py
amazon/category/actions/__init__.py
amazon/category/actions/amazon_category.py
amazon/category/actions/parsers.py
amazon/category/management/__init__.py
amazon/category/management/commands/__init__.py
amazon/category/management/commands/create_amazon_categories.py
amazon/category/management/commands/delete_amazon_categories.py
amazon/category/migrations/0001_initial.py
amazon/category/migrations/0002_auto_20200117_1440.py
amazon/category/migrations/__init__.py
amazon/category/models/__init__.py
amazon/category/models/amazon_category.py
amazon/data/__init__.py
amazon/data/domain_name_to_marketplace.py
amazon/data/enums/__init__.py
amazon/data/enums/common_enums.py
amazon/data/enums/feed_enums.py
amazon/data/enums/product_categories_enum.py
etsy_api_zs-0.4.dist-info/METADATA
etsy_api_zs-0.4.dist-info/WHEEL
etsy_api_zs-0.4.dist-info/top_level.txt
etsy_api_zs-0.4.dist-info/RECORD
